{"_meta":{"description":"This file contains a serialized version of schema entities for drift.","version":"1.1.0"},"options":{"store_date_time_values_as_text":false},"entities":[{"id":0,"references":[],"type":"table","data":{"name":"recipes","was_declared_in_moor":false,"columns":[{"name":"id","getter_name":"id","moor_type":"int","nullable":false,"customConstraints":null,"defaultConstraints":"PRIMARY KEY AUTOINCREMENT","default_dart":null,"default_client_dart":null,"dsl_features":["auto-increment"]},{"name":"title","getter_name":"title","moor_type":"string","nullable":false,"customConstraints":null,"default_dart":null,"default_client_dart":null,"dsl_features":[]},{"name":"ingredients","getter_name":"ingredients","moor_type":"string","nullable":false,"customConstraints":null,"default_dart":null,"default_client_dart":null,"dsl_features":[],"type_converter":{"dart_expr":"const StringListConverter()","dart_type_name":"List<String>"}},{"name":"instructions","getter_name":"instructions","moor_type":"string","nullable":false,"customConstraints":null,"default_dart":null,"default_client_dart":null,"dsl_features":[],"type_converter":{"dart_expr":"const StringListConverter()","dart_type_name":"List<String>"}},{"name":"cook_time","getter_name":"cookTime","moor_type":"int","nullable":false,"customConstraints":null,"default_dart":null,"default_client_dart":null,"dsl_features":[]},{"name":"notes","getter_name":"notes","moor_type":"string","nullable":false,"customConstraints":null,"default_dart":null,"default_client_dart":null,"dsl_features":[]},{"name":"save_at","getter_name":"saveAt","moor_type":"int","nullable":false,"customConstraints":null,"default_dart":null,"default_client_dart":null,"dsl_features":[]},{"name":"image_u_r_l","getter_name":"imageURL","moor_type":"string","nullable":true,"customConstraints":null,"default_dart":null,"default_client_dart":null,"dsl_features":[]},{"name":"saving_summary_c_o2","getter_name":"savingSummary_CO2","moor_type":"int","nullable":false,"customConstraints":null,"default_dart":null,"default_client_dart":null,"dsl_features":[]},{"name":"saving_summary_money","getter_name":"savingSummary_money","moor_type":"int","nullable":false,"customConstraints":null,"default_dart":null,"default_client_dart":null,"dsl_features":[]}],"is_virtual":false,"without_rowid":false,"constraints":[]}}]}